__init__.py
annotation_setup.py
answer_generation.py
image_extraction.py
init.py
model.py
question_extraction.py
transformer.py
vqa/__init__.py
vqa/app.py
vqa/mvqa.py
vqa/src/__init__.py
vqa/src/annotation_setup.py
vqa/src/answer_generation.py
vqa/src/image_extraction.py
vqa/src/init.py
vqa/src/model.py
vqa/src/question_extraction.py
vqa/src/root_dir.py
vqa/src/transformer.py
vqa/src/extraction/image_extraction.py
vqa/src/extraction/question_extraction.py
vqa/storage/__init__.py
vqa/storage/config.yml
vqa/storage/dictionary.json
vlmvqa_python-0.0.4.dist-info/METADATA
vlmvqa_python-0.0.4.dist-info/WHEEL
vlmvqa_python-0.0.4.dist-info/top_level.txt
vlmvqa_python-0.0.4.dist-info/RECORD
